pycabinet/__init__.py
pycabinet/pycabinet.py
pycabinet/test.py
pycabinet-0.0.2.dist-info/LICENSE
pycabinet-0.0.2.dist-info/METADATA
pycabinet-0.0.2.dist-info/WHEEL
pycabinet-0.0.2.dist-info/top_level.txt
pycabinet-0.0.2.dist-info/RECORD
